cdktf_multi_stack_tfe/__init__.py
cdktf_multi_stack_tfe/py.typed
cdktf_multi_stack_tfe/_jsii/__init__.py
cdktf_multi_stack_tfe/_jsii/cdktf-multi-stack-tfe@0.0.96.jsii.tgz
cdktf_multi_stack_tfe-0.0.96.dist-info/LICENSE
cdktf_multi_stack_tfe-0.0.96.dist-info/METADATA
cdktf_multi_stack_tfe-0.0.96.dist-info/WHEEL
cdktf_multi_stack_tfe-0.0.96.dist-info/top_level.txt
cdktf_multi_stack_tfe-0.0.96.dist-info/RECORD
