Metadata-Version: 2.1
Name: cdktf-multi-stack-tfe
Version: 0.0.96
Summary: Sets up TFE / TFC workspaces for all stacks based on a seed stack.
Home-page: https://github.com/DanielMSchmidt/cdktf-multi-stack-tfe.git
Author: Daniel Schmidt<danielmschmidt92@gmail.com>
License: MIT
Project-URL: Source, https://github.com/DanielMSchmidt/cdktf-multi-stack-tfe.git
Platform: UNKNOWN
Classifier: Intended Audience :: Developers
Classifier: Operating System :: OS Independent
Classifier: Programming Language :: JavaScript
Classifier: Programming Language :: Python :: 3 :: Only
Classifier: Programming Language :: Python :: 3.7
Classifier: Programming Language :: Python :: 3.8
Classifier: Programming Language :: Python :: 3.9
Classifier: Programming Language :: Python :: 3.10
Classifier: Typing :: Typed
Classifier: Development Status :: 5 - Production/Stable
Classifier: License :: OSI Approved
Requires-Python: ~=3.7
License-File: LICENSE
Requires-Dist: cdktf-cdktf-provider-tfe (>=0.2.0)
Requires-Dist: cdktf (<0.11.0,>=0.10.1)
Requires-Dist: constructs (<11.0.0,>=10.0.107)
Requires-Dist: jsii (<2.0.0,>=1.58.0)
Requires-Dist: publication (>=0.0.3)
